{
	"type": "普通",
	"list": [
		{
			"label": "长期事项",
			"status": "todo",
			"priority": 1
		},
		{
			"label": "父项事项",
			"group": [
				{
					"label": "子项事项",
					"status": "todo",
					"priority": 0
				}
			],
			"priority": 0
		},
		{
			"label": "单次事项",
			"status": "todo",
			"time": "2021/12/20-18:00",
			"priority": 0
		},
		{
			"label": "每日事项",
			"status": "todo",
			"cycle": "daily",
			"time": "2021/12/20-18:00",
			"priority": 0,
			"place": "地点"
		},
		{
			"label": "每周事项",
			"status": "todo",
			"cycle": "weekly",
			"time": "2021/12/22-18:00",
			"priority": 0
		}
	]
}